<?xml version="1.0" encoding="UTF-8"?>
<vocab>
	<title>Common Ways to Say Sorry</title>
	<word>
		<english>I won't do it again</english>
		<romaji>Mō shimasen</romaji>
	</word>

	<word>
		<english>I didn't mean that.</english>
		<romaji>Sō iu tsumori de wa arimasen deshita</romaji>
	</word>

	<word>
		<english>It's my fault</english>
		<romaji>Watashi no sei desu</romaji>
	</word>

	<word>
		<english>I'm sorry</english>
		<romaji>gomen nasai</romaji>
	</word>

	<word>
		<english>I hope you forgive me</english>
		<romaji>watashi wa anata ga watashi o yurushite kureru koto o negatte imasu.
</romaji>
	</word>

	<word>
		<english>I take full responsibility</english>
		<romaji>watashi ga zensekinin o oimasu</romaji>
	</word>

	<word>
		<english>I would like to apologize</english>
		<romaji>watashi wa shazaishitai desu</romaji>
	</word>

	<word>
		<english>I'll make sure not to make this mistake again</english>
		<romaji>watashi wa kono yōna machigai o nidoto shinai yōni shimasu.</romaji>
	</word>

	<word>
		<english>I sincerely apologize</english>
		<romaji>watashi wa kokoro kara owabi mōshi agemasu</romaji>
	</word>

	<word>
		<english>I shouldn't have done it</english>
		<romaji>watashi wa sore o suru beki dewa arimasendeshita.
</romaji>
	</word>

	<word>
		<english>Sorry for giving your money back late</english>
		<romaji>anata no okane o kaesu no ga osokunatte gomen nasai.</romaji>
	</word>

	<word>
		<english>Please don't be mad at me</english>
		<romaji>watashi ni okoranaide kudasai.
</romaji>
	</word>

	<word>
		<english>Sorry I'm late</english>
		<romaji>okurete sumimasen</romaji>
	</word>

	<word>
		<english>I apologize for being mean to you</english>
		<romaji>anata ni shitsureina taido o totta koto o owabishimasu.</romaji>
	</word>

	<word>
		<english>I'm sorry for being selfish</english>
		<romaji>wagamama de gomen nasai.
</romaji>
	</word>
	
</vocab>
